{
  "appPageId" : "1f9afd36-7ca0-451b-a07b-58308ca4b970",
  "componentName" : "siteforce:sldsOneColLayout",
  "id" : "b915c2ef-2128-4ef6-93ce-d3ef7455746f",
  "label" : "Service Not Available",
  "regions" : [ {
    "components" : [ {
      "componentAttributes" : {
        "richTextValue" : "<div style='display: flex; align-items: center; flex-direction: column; margin: 60px 25px 40px 25px;'><div style='background: url(/sfsites/assets/Images/serviceNotAvailable/serviceNotAvailable.svg) center no-repeat; background-size: contain; height: 331px; width: 100%; max-width: 538px;'></div></div><div style='margin: 0 25px; text-align: center;'><p><b style='font-size: 3.4em'>Looks like the site is temporarily unavailable</b></p><br/><p><span style='font-size: 2em;'>Please try again in a bit.</span></p></div>"
      },
      "componentName" : "forceCommunity:htmlBlock",
      "id" : "799184a2-d017-4e74-b988-3394731c9dab",
      "renderPriority" : "NEUTRAL",
      "renditionMap" : { },
      "type" : "component"
    } ],
    "id" : "f5d9b83d-f51c-4ae5-851e-e69d2a1f5890",
    "regionName" : "content",
    "type" : "region"
  } ],
  "themeLayoutType" : "ServiceNotAvailable",
  "type" : "view",
  "viewType" : "service-not-available"
}